linestats/__init__.py
linestats/__main__.py
linestats/linestats.py
linestats/version.py
linestats-1.2.1.dist-info/AUTHORS
linestats-1.2.1.dist-info/LICENSE
linestats-1.2.1.dist-info/METADATA
linestats-1.2.1.dist-info/WHEEL
linestats-1.2.1.dist-info/entry_points.txt
linestats-1.2.1.dist-info/top_level.txt
linestats-1.2.1.dist-info/RECORD
