Metadata-Version: 2.1
Name: linestats
Version: 1.2.1
Summary: Python module to count the number of scripted, commented, docstringed, and empty lines in Python code.
Home-page: https://github.com/fpavogt/linestats
Author: fpavogt
Author-email: frederic.vogt@alumni.anu.edu.au
License: GNU General Public License v3 or later (GPLv3+)
Download-URL: https://github.com/fpavogt/linestats/archive/master.zip
Project-URL: Source, https://github.com/fpavogt/linestats
Project-URL: Changelog, https://github.com/fpavogt/linestats#changelog
Project-URL: Issues, https://github.com/fpavogt/linestats/issues
Platform: UNKNOWN
Classifier: Development Status :: 4 - Beta
Classifier: License :: OSI Approved :: GNU General Public License v3 or later (GPLv3+)
Classifier: Programming Language :: Python :: 3
Classifier: Programming Language :: Python :: 3.8
Classifier: Programming Language :: Python :: 3.9
Classifier: Programming Language :: Python :: 3.10
Requires-Python: >=3
License-File: LICENSE
License-File: AUTHORS
